avem_theme/__init__.py
avem_theme/context.py
avem_theme/__pycache__/__init__.cpython-36.pyc
avem_theme/__pycache__/context.cpython-36.pyc
avem_theme/functions/__init__.py
avem_theme/functions/hashing.py
avem_theme/functions/list_sample.py
avem_theme/functions/sanitize.py
avem_theme/functions/__pycache__/__init__.cpython-36.pyc
avem_theme/functions/__pycache__/hashing.cpython-36.pyc
avem_theme/functions/__pycache__/list_sample.cpython-36.pyc
avem_theme/functions/__pycache__/sanitize.cpython-36.pyc
avem_theme/static/admin_inline_model_name_hack.css
avem_theme/static/bootstrap3-typeahead.min.js
avem_theme/static/jquery-2.1.4.min.js
avem_theme/static/avem/script.js
avem_theme/static/avem/style.css
avem_theme/static/bootstrap-3.3.5/css/bootstrap.min.css
avem_theme/static/bootstrap-3.3.5/fonts/glyphicons-halflings-regular.eot
avem_theme/static/bootstrap-3.3.5/fonts/glyphicons-halflings-regular.svg
avem_theme/static/bootstrap-3.3.5/fonts/glyphicons-halflings-regular.ttf
avem_theme/static/bootstrap-3.3.5/fonts/glyphicons-halflings-regular.woff
avem_theme/static/bootstrap-3.3.5/fonts/glyphicons-halflings-regular.woff2
avem_theme/static/bootstrap-3.3.5/js/bootstrap.min.js
avem_theme/templates/admin_override/base_site.html
avem_theme/templates/avem/base.html
avem_theme/templates/avem/frame.html
avem_theme/templates/avem/menu_items_account.html
avem_theme/templates/avem/menu_items_login.html
avem_theme/templates/avem/menu_right.html
avem_theme/templatetags/__init__.py
avem_theme/templatetags/ext.py
avem_theme/templatetags/__pycache__/__init__.cpython-36.pyc
avem_theme/templatetags/__pycache__/ext.cpython-36.pyc
django_avem_theme-2.0.1.dist-info/LICENSE.txt
django_avem_theme-2.0.1.dist-info/METADATA
django_avem_theme-2.0.1.dist-info/WHEEL
django_avem_theme-2.0.1.dist-info/top_level.txt
django_avem_theme-2.0.1.dist-info/RECORD
