Metadata-Version: 2.1
Name: django-avem-theme
Version: 2.0.1
Summary: Simple bootstrap3 theme for Django
Home-page: https://github.com/mverleg/django_avem_theme
Author: Mark V
Author-email: mdilligaf@gmail.com
Maintainer: (the author)
License: Revised BSD License (LICENSE.txt)
Keywords: django,bootstrap
Platform: UNKNOWN
Classifier: Development Status :: 2 - Pre-Alpha
Classifier: License :: OSI Approved :: BSD License
Requires-Dist: django
